{
  "Central": {
    "Food Products": 1327,
    "Beverages": 770,
    "Tobacco": 5,
    "Textiles": 13,
    "Leather and Leather Products": 138,
    "Wood and Wood Products": 204,
    "Paper and Paper Products": 196,
    "Printing and Reproduction of Recorded Media": 775,
    "Coke and Petroleum Products": 74,
    "Chemical and Chemical Products": 641,
    "Pharmaceutical, Medical Chemicals and Botanical Products": 86,
    "Rubber and Plastic Products": 338,
    "Other Non-Metallic Mineral Products": 221,
    "Basic Metals": 158,
    "Fabricated Metal Products Except Machinery and Equipment": 357,
    "Computer, Electronic and Optical Products": 2,
    "Electrical Equipment": 79,
    "Machinery and Equipment": 5,
    "Motor Vehicles, Trailers and Semi-Trailers": 14,
    "Other Transport Equipment": 29,
    "Other Manufacturing": 14
  },
  "Eastern": {
    "Food Products": 218,
    "Beverages": 71,
    "Tobacco": 1,
    "Textiles": 6,
    "Leather and Leather Products": 18,
    "Wood and Wood Products": 25,
    "Paper and Paper Products": 14,
    "Printing and Reproduction of Recorded Media": 9,
    "Coke and Petroleum Products": 9,
    "Chemical and Chemical Products": 37,
    "Pharmaceutical, Medical Chemicals and Botanical Products": 6,
    "Rubber and Plastic Products": 19,
    "Other Non-Metallic Mineral Products": 27,
    "Basic Metals": 23,
    "Fabricated Metal Products Except Machinery and Equipment": 34,
    "Electrical Equipment": 12,
    "Machinery and Equipment": 3,
    "Motor Vehicles, Trailers and Semi-Trailers": 3,
    "Other Manufacturing": 3
  },
  "Western": {
    "Food Products": 214,
    "Beverages": 221,
    "Textiles": 1,
    "Leather and Leather Products": 6,
    "Wood and Wood Products": 23,
    "Paper and Paper Products": 4,
    "Printing and Reproduction of Recorded Media": 13,
    "Coke and Petroleum Products": 3,
    "Chemical and Chemical Products": 33,
    "Pharmaceutical, Medical Chemicals and Botanical Products": 4,
    "Rubber and Plastic Products": 5,
    "Other Non-Metallic Mineral Products": 13,
    "Basic Metals": 7,
    "Fabricated Metal Products Except Machinery and Equipment": 22,
    "Motor Vehicles, Trailers and Semi-Trailers": 1
  },
  "Northern": {
    "Food Products": 154,
    "Beverages": 60,
    "Tobacco": 1,
    "Textiles": 1,
    "Leather and Leather Products": 6,
    "Wood and Wood Products": 13,
    "Printing and Reproduction of Recorded Media": 10,
    "Coke and Petroleum Products": 3,
    "Chemical and Chemical Products": 11,
    "Other Non-Metallic Mineral Products": 4,
    "Basic Metals": 3,
    "Fabricated Metal Products Except Machinery and Equipment": 28
  },
  "Unclassified": {
    "Food Products": 39,
    "Beverages": 43,
    "Tobacco": 1,
    "Leather and Leather Products": 8,
    "Wood and Wood Products": 6,
    "Paper and Paper Products": 9,
    "Printing and Reproduction of Recorded Media": 1,
    "Coke and Petroleum Products": 4,
    "Chemical and Chemical Products": 26,
    "Pharmaceutical, Medical Chemicals and Botanical Products": 2,
    "Rubber and Plastic Products": 4,
    "Other Non-Metallic Mineral Products": 7,
    "Basic Metals": 3,
    "Fabricated Metal Products Except Machinery and Equipment": 8,
    "Electrical Equipment": 1,
    "Motor Vehicles, Trailers and Semi-Trailers": 1
  }
}